firesynth/__init__.py
firesynth/config.py
firesynth/generators.py
firesynth/indices.py
firesynth/utils.py
firesynth_s2-0.1.2.dist-info/METADATA
firesynth_s2-0.1.2.dist-info/WHEEL
firesynth_s2-0.1.2.dist-info/top_level.txt
firesynth_s2-0.1.2.dist-info/RECORD
