Metadata-Version: 2.4
Name: firesynth-s2
Version: 0.1.2
Summary: Physically-informed Sentinel-2 wildfire-risk spectral simulator
Author-email: Your Name <your@email.com>
License: MIT
Project-URL: Homepage, https://github.com/yourname/firesynth-s2
Requires-Python: >=3.8
Requires-Dist: numpy
Requires-Dist: pandas
